fundar/__init__.py
fundar/colores.py
fundar/fuzzy.py
fundar/googledrive.py
fundar/json.py
fundar/languages.py
fundar/py.typed
fundar/structures.py
fundar/translate.py
fundar/llms/__init__.py
fundar/llms/__init__.pyi
fundar/llms/_types.pyi
fundar/llms/cuda.pyi
fundar/llms/api/__init__.pyi
fundar/llms/api/interface.pyi
fundar/llms/api/ollama.pyi
fundar/llms/api/tokenizers.pyi
fundar/llms/dimred/__init__.pyi
fundar/llms/dimred/projections.pyi
fundar/llms/dimred/tsne.pyi
fundar/llms/dimred/umap.pyi
fundar/llms/reranking/__init__.pyi
fundar/llms/reranking/cross_encoder.pyi
fundar/llms/utils/__init__.pyi
fundar/llms/utils/_dataclass.pyi
fundar/llms/utils/common.pyi
fundar/llms/utils/models.pyi
fundar/llms/utils/uuid.pyi
fundar/llms/vectorization/__init__.pyi
fundar/llms/vectorization/documents.pyi
fundar/pandas/__init__.py
fundar/pandas/utils.py
fundar/parallelization/__init__.py
fundar/parallelization/pools.py
fundar/polars/__init__.py
fundar/polars/polars.py
fundar/utils/__init__.py
fundar/utils/operators.py
fundar/utils/time.py
fundar-1.0.11.dist-info/METADATA
fundar-1.0.11.dist-info/WHEEL
fundar-1.0.11.dist-info/top_level.txt
fundar-1.0.11.dist-info/RECORD
