Metadata-Version: 2.1
Name: fundar
Version: 1.0.11
Summary: Private Python library.
Author: Fundar
Requires-Python: >=3.10
